{
  "inferno_utb": {
    "name": "inferno 3.10.1",
    "description": "An extremely fast, React-like JavaScript library for building modern user interfaces",
    "homepage": "https://github.com/infernojs/inferno#readme",
    "examples": [
      {
        "name": "lom_atom 3.1.0",
        "url": "examples/inferno-lom_atom"
      },
      {
        "name": "lom_atom 3.1.0 + reactive-di 6.0.8",
        "url": "examples/inferno-lom_atom--reactive-di"
      },
      {
        "name": "mobx 3.4.1 + mobx-react 4.3.5",
        "url": "examples/inferno-mobx--mobx-react"
      },
      {
        "name": "mobx 3.4.1 + reactive-di 6.0.8",
        "url": "examples/inferno-mobx--reactive-di"
      },
      {
        "name": "raw",
        "url": "examples/inferno-raw"
      },
      {
        "name": "redux 3.7.2 + react-redux 5.0.6",
        "url": "examples/inferno-redux--react-redux"
      }
    ]
  },
  "preact_utb": {
    "name": "preact 8.2.7",
    "description": "Fast 3kb React alternative with the same ES6 API. Components & Virtual DOM.",
    "homepage": "https://github.com/developit/preact",
    "examples": [
      {
        "name": "lom_atom 3.1.0",
        "url": "examples/preact-lom_atom"
      },
      {
        "name": "lom_atom 3.1.0 + reactive-di 6.0.8",
        "url": "examples/preact-lom_atom--reactive-di"
      },
      {
        "name": "mobx 3.4.1 + mobx-react 4.3.5",
        "url": "examples/preact-mobx--mobx-react"
      },
      {
        "name": "mobx 3.4.1 + reactive-di 6.0.8",
        "url": "examples/preact-mobx--reactive-di"
      },
      {
        "name": "raw",
        "url": "examples/preact-raw"
      },
      {
        "name": "redux 3.7.2 + react-redux 5.0.6",
        "url": "examples/preact-redux--react-redux"
      }
    ]
  },
  "react_utb": {
    "name": "react 16.2.0",
    "description": "React is a JavaScript library for building user interfaces.",
    "homepage": "https://reactjs.org/",
    "examples": [
      {
        "name": "lom_atom 3.1.0",
        "url": "examples/react-lom_atom"
      },
      {
        "name": "lom_atom 3.1.0 + reactive-di 6.0.8",
        "url": "examples/react-lom_atom--reactive-di"
      },
      {
        "name": "mobx 3.4.1 + mobx-react 4.3.5",
        "url": "examples/react-mobx--mobx-react"
      },
      {
        "name": "mobx 3.4.1 + reactive-di 6.0.8",
        "url": "examples/react-mobx--reactive-di"
      },
      {
        "name": "raw",
        "url": "examples/react-raw"
      },
      {
        "name": "redux 3.7.2 + react-redux 5.0.6",
        "url": "examples/react-redux--react-redux"
      }
    ]
  }
}